geometry_api_v2-1.11.0.dist-info/licenses/LICENSE
shapediver/geometry_api_v2/__init__.py
shapediver/geometry_api_v2/sd_client.py
shapediver/geometry_api_v2/sd_utils.py
shapediver/geometry_api_v2/client/__init__.py
shapediver/geometry_api_v2/client/api_client.py
shapediver/geometry_api_v2/client/api_response.py
shapediver/geometry_api_v2/client/configuration.py
shapediver/geometry_api_v2/client/exceptions.py
shapediver/geometry_api_v2/client/py.typed
shapediver/geometry_api_v2/client/rest.py
shapediver/geometry_api_v2/client/api/__init__.py
shapediver/geometry_api_v2/client/api/analytics_api.py
shapediver/geometry_api_v2/client/api/ar_scene_api.py
shapediver/geometry_api_v2/client/api/assets_api.py
shapediver/geometry_api_v2/client/api/auth_api.py
shapediver/geometry_api_v2/client/api/auth_group_api.py
shapediver/geometry_api_v2/client/api/export_api.py
shapediver/geometry_api_v2/client/api/file_api.py
shapediver/geometry_api_v2/client/api/gltf_api.py
shapediver/geometry_api_v2/client/api/log_api.py
shapediver/geometry_api_v2/client/api/model_api.py
shapediver/geometry_api_v2/client/api/model_state_api.py
shapediver/geometry_api_v2/client/api/output_api.py
shapediver/geometry_api_v2/client/api/script_api.py
shapediver/geometry_api_v2/client/api/sdtf_api.py
shapediver/geometry_api_v2/client/api/session_api.py
shapediver/geometry_api_v2/client/api/system_api.py
shapediver/geometry_api_v2/client/api/texture_api.py
shapediver/geometry_api_v2/client/models/__init__.py
shapediver/geometry_api_v2/client/models/commmons_parameter_asset.py
shapediver/geometry_api_v2/client/models/commons_basic_parameter.py
shapediver/geometry_api_v2/client/models/commons_computation_status.py
shapediver/geometry_api_v2/client/models/commons_group.py
shapediver/geometry_api_v2/client/models/commons_model_blocking_reasons.py
shapediver/geometry_api_v2/client/models/commons_model_status.py
shapediver/geometry_api_v2/client/models/commons_parameter_chunk.py
shapediver/geometry_api_v2/client/models/commons_stype_parameter.py
geometry_api_v2-1.11.0.dist-info/METADATA
geometry_api_v2-1.11.0.dist-info/WHEEL
geometry_api_v2-1.11.0.dist-info/top_level.txt
geometry_api_v2-1.11.0.dist-info/RECORD
