Metadata-Version: 2.4
Name: geometry_api_v2
Version: 1.11.0
Summary: SDK to communicate with the ShapeDiver Geometry API version 2
Home-page: https://shapediver.com/
Author: ShapeDiver
Author-email: dev@shapediver.com
License: MIT
Project-URL: Documentation, https://help.shapediver.com/doc/geometry-backend
Project-URL: Source, https://github.com/shapediver/GeometryBackendSdkPython
Keywords: shapediver,gb-api,sdk
Platform: any
Classifier: Development Status :: 5 - Production/Stable
Classifier: Programming Language :: Python
Requires-Python: >=3.9
License-File: LICENSE
Requires-Dist: python_dateutil>=2.5.3
Requires-Dist: setuptools>=21.0.0
Requires-Dist: urllib3<3.0.0,>=2.1.0
Requires-Dist: pydantic>=2
Requires-Dist: typing-extensions>=4.7.1
Provides-Extra: testing
Requires-Dist: setuptools; extra == "testing"
Requires-Dist: pytest; extra == "testing"
Requires-Dist: pytest-cov; extra == "testing"
Dynamic: license-file
